es_search_exporter/__init__.py
es_search_exporter/collector.py
es_search_exporter/http.py
es_search_exporter-0.2.0.data/scripts/es_search_exporter
es_search_exporter-0.2.0.dist-info/DESCRIPTION.rst
es_search_exporter-0.2.0.dist-info/METADATA
es_search_exporter-0.2.0.dist-info/RECORD
es_search_exporter-0.2.0.dist-info/WHEEL
es_search_exporter-0.2.0.dist-info/metadata.json
es_search_exporter-0.2.0.dist-info/top_level.txt
