Metadata-Version: 2.0
Name: es-search-exporter
Version: 0.2.0
Summary: Elasticsearch search exporter for the Prometheus monitoring system.
Home-page: https://github.com/ipstatic/es_search_exporter
Author: Jarod Watkins
Author-email: jarod@42lines.net
License: MIT
Keywords: prometheus exporter network monitoring elastic search
Platform: UNKNOWN
Classifier: Development Status :: 3 - Alpha
Classifier: Intended Audience :: Information Technology
Classifier: Intended Audience :: System Administrators
Classifier: Topic :: System :: Monitoring
Classifier: License :: OSI Approved :: MIT License
Requires-Dist: prometheus-client (>=0.0.14)
Requires-Dist: pyyaml (>=3.11)
Requires-Dist: requests (>=2.10.0)
Requires-Dist: requests-kerberos (>=0.10.0)
